<cacti>	
	<hash_0001017489e44466abee8a7d8636cb2cb14a1a>
		<name>Host MIB - Available Disk Space</name>
		<graph>
			<t_title>on</t_title>
			<title>|host_description| - Available Disk Space</title>
			<t_vertical_label></t_vertical_label>
			<vertical_label>Bytes</vertical_label>
			<t_image_format_id></t_image_format_id>
			<image_format_id>1</image_format_id>
			<t_height></t_height>
			<height>200</height>
			<t_width></t_width>
			<width>700</width>
			<t_base_value></t_base_value>
			<base_value>1000</base_value>
			<t_slope_mode></t_slope_mode>
			<slope_mode>on</slope_mode>
			<t_auto_scale></t_auto_scale>
			<auto_scale>on</auto_scale>
			<t_auto_scale_opts></t_auto_scale_opts>
			<auto_scale_opts>2</auto_scale_opts>
			<t_auto_scale_log></t_auto_scale_log>
			<auto_scale_log></auto_scale_log>
			<t_scale_log_units></t_scale_log_units>
			<scale_log_units></scale_log_units>
			<t_auto_scale_rigid></t_auto_scale_rigid>
			<auto_scale_rigid>on</auto_scale_rigid>
			<t_upper_limit></t_upper_limit>
			<upper_limit>100</upper_limit>
			<t_lower_limit></t_lower_limit>
			<lower_limit>0</lower_limit>
			<t_unit_value></t_unit_value>
			<unit_value></unit_value>
			<t_unit_exponent_value></t_unit_exponent_value>
			<unit_exponent_value></unit_exponent_value>
			<t_unit_length></t_unit_length>
			<unit_length></unit_length>
			<t_no_gridfit></t_no_gridfit>
			<no_gridfit></no_gridfit>
			<t_alt_y_grid></t_alt_y_grid>
			<alt_y_grid></alt_y_grid>
			<t_right_axis></t_right_axis>
			<right_axis></right_axis>
			<t_right_axis_label></t_right_axis_label>
			<right_axis_label></right_axis_label>
			<t_right_axis_format></t_right_axis_format>
			<right_axis_format>0</right_axis_format>
			<t_right_axis_formatter></t_right_axis_formatter>
			<right_axis_formatter>0</right_axis_formatter>
			<t_left_axis_formatter></t_left_axis_formatter>
			<left_axis_formatter>0</left_axis_formatter>
			<t_auto_padding></t_auto_padding>
			<auto_padding>on</auto_padding>
			<t_dynamic_labels></t_dynamic_labels>
			<dynamic_labels></dynamic_labels>
			<t_force_rules_legend></t_force_rules_legend>
			<force_rules_legend></force_rules_legend>
			<t_tab_width></t_tab_width>
			<tab_width>40</tab_width>
			<t_legend_position></t_legend_position>
			<legend_position>0</legend_position>
			<t_legend_direction></t_legend_direction>
			<legend_direction>0</legend_direction>
		</graph>
		<items>
			<hash_100101d80e4a4901ab86ee39c9cc613e13532f>
				<graph_type_id>7</graph_type_id>
				<task_item_id>hash_080101165a0da5f461561c85d092dfe96b9551</task_item_id>
				<color_id>002A97</color_id>
				<alpha>7F</alpha>
				<consolidation_function_id>1</consolidation_function_id>
				<cdef_id>0</cdef_id>
				<vdef_id>0</vdef_id>
				<shift></shift>
				<value></value>
				<gprint_id>hash_060101e9c43831e54eca8069317a2ce8c6f751</gprint_id>
				<textalign></textalign>
				<text_format>Total</text_format>
				<hard_return></hard_return>
				<line_width>0.00</line_width>
				<dashes></dashes>
				<dash_offset>0</dash_offset>
				<sequence>1</sequence>
			</hash_100101d80e4a4901ab86ee39c9cc613e13532f>
			<hash_100101567c2214ee4753aa712c3d101ea49a5d>
				<graph_type_id>9</graph_type_id>
				<task_item_id>hash_080101165a0da5f461561c85d092dfe96b9551</task_item_id>
				<color_id>0</color_id>
				<alpha>FF</alpha>
				<consolidation_function_id>4</consolidation_function_id>
				<cdef_id>0</cdef_id>
				<vdef_id>0</vdef_id>
				<shift></shift>
				<value></value>
				<gprint_id>hash_060101e9c43831e54eca8069317a2ce8c6f751</gprint_id>
				<textalign></textalign>
				<text_format>Current:</text_format>
				<hard_return></hard_return>
				<line_width>0.00</line_width>
				<dashes></dashes>
				<dash_offset>0</dash_offset>
				<sequence>2</sequence>
			</hash_100101567c2214ee4753aa712c3d101ea49a5d>
			<hash_100101ba0b6a9e316ef9be66abba68b80f7587>
				<graph_type_id>9</graph_type_id>
				<task_item_id>hash_080101165a0da5f461561c85d092dfe96b9551</task_item_id>
				<color_id>0</color_id>
				<alpha>FF</alpha>
				<consolidation_function_id>1</consolidation_function_id>
				<cdef_id>0</cdef_id>
				<vdef_id>0</vdef_id>
				<shift></shift>
				<value></value>
				<gprint_id>hash_060101e9c43831e54eca8069317a2ce8c6f751</gprint_id>
				<textalign></textalign>
				<text_format>Average:</text_format>
				<hard_return></hard_return>
				<line_width>0.00</line_width>
				<dashes></dashes>
				<dash_offset>0</dash_offset>
				<sequence>3</sequence>
			</hash_100101ba0b6a9e316ef9be66abba68b80f7587>
			<hash_1001014b8e4a6bf2757f04c3e3a088338a2f7a>
				<graph_type_id>9</graph_type_id>
				<task_item_id>hash_080101165a0da5f461561c85d092dfe96b9551</task_item_id>
				<color_id>0</color_id>
				<alpha>FF</alpha>
				<consolidation_function_id>3</consolidation_function_id>
				<cdef_id>0</cdef_id>
				<vdef_id>0</vdef_id>
				<shift></shift>
				<value></value>
				<gprint_id>hash_060101e9c43831e54eca8069317a2ce8c6f751</gprint_id>
				<textalign></textalign>
				<text_format>Maximum:</text_format>
				<hard_return>on</hard_return>
				<line_width>0.00</line_width>
				<dashes></dashes>
				<dash_offset>0</dash_offset>
				<sequence>4</sequence>
			</hash_1001014b8e4a6bf2757f04c3e3a088338a2f7a>
			<hash_10010116d6a9a7f608762ad65b0841e5ef4e9c>
				<graph_type_id>7</graph_type_id>
				<task_item_id>hash_0801010ee6bb54957f6795a5369a29f818d860</task_item_id>
				<color_id>F51D30</color_id>
				<alpha>7F</alpha>
				<consolidation_function_id>1</consolidation_function_id>
				<cdef_id>0</cdef_id>
				<vdef_id>0</vdef_id>
				<shift></shift>
				<value></value>
				<gprint_id>hash_060101e9c43831e54eca8069317a2ce8c6f751</gprint_id>
				<textalign></textalign>
				<text_format>Used</text_format>
				<hard_return></hard_return>
				<line_width>0.00</line_width>
				<dashes></dashes>
				<dash_offset>0</dash_offset>
				<sequence>5</sequence>
			</hash_10010116d6a9a7f608762ad65b0841e5ef4e9c>
			<hash_1001012c35b5cae64c5f146a55fcb416dd14b5>
				<graph_type_id>9</graph_type_id>
				<task_item_id>hash_0801010ee6bb54957f6795a5369a29f818d860</task_item_id>
				<color_id>0</color_id>
				<alpha>FF</alpha>
				<consolidation_function_id>4</consolidation_function_id>
				<cdef_id>0</cdef_id>
				<vdef_id>0</vdef_id>
				<shift></shift>
				<value></value>
				<gprint_id>hash_060101e9c43831e54eca8069317a2ce8c6f751</gprint_id>
				<textalign></textalign>
				<text_format>Current:</text_format>
				<hard_return></hard_return>
				<line_width>0.00</line_width>
				<dashes></dashes>
				<dash_offset>0</dash_offset>
				<sequence>6</sequence>
			</hash_1001012c35b5cae64c5f146a55fcb416dd14b5>
			<hash_10010136fa8063df3b07cece878d54443db727>
				<graph_type_id>9</graph_type_id>
				<task_item_id>hash_0801010ee6bb54957f6795a5369a29f818d860</task_item_id>
				<color_id>0</color_id>
				<alpha>FF</alpha>
				<consolidation_function_id>1</consolidation_function_id>
				<cdef_id>0</cdef_id>
				<vdef_id>0</vdef_id>
				<shift></shift>
				<value></value>
				<gprint_id>hash_060101e9c43831e54eca8069317a2ce8c6f751</gprint_id>
				<textalign></textalign>
				<text_format>Average:</text_format>
				<hard_return></hard_return>
				<line_width>0.00</line_width>
				<dashes></dashes>
				<dash_offset>0</dash_offset>
				<sequence>7</sequence>
			</hash_10010136fa8063df3b07cece878d54443db727>
			<hash_100101b7b381d47972f836785d338a3bef6661>
				<graph_type_id>9</graph_type_id>
				<task_item_id>hash_0801010ee6bb54957f6795a5369a29f818d860</task_item_id>
				<color_id>0</color_id>
				<alpha>FF</alpha>
				<consolidation_function_id>3</consolidation_function_id>
				<cdef_id>0</cdef_id>
				<vdef_id>0</vdef_id>
				<shift></shift>
				<value></value>
				<gprint_id>hash_060101e9c43831e54eca8069317a2ce8c6f751</gprint_id>
				<textalign></textalign>
				<text_format>Maximum:</text_format>
				<hard_return>on</hard_return>
				<line_width>0.00</line_width>
				<dashes></dashes>
				<dash_offset>0</dash_offset>
				<sequence>8</sequence>
			</hash_100101b7b381d47972f836785d338a3bef6661>
			<hash_100101fd1f89bda6ca439507b8b10a6895ef83>
				<graph_type_id>4</graph_type_id>
				<task_item_id>hash_080101165a0da5f461561c85d092dfe96b9551</task_item_id>
				<color_id>002A97</color_id>
				<alpha>FF</alpha>
				<consolidation_function_id>1</consolidation_function_id>
				<cdef_id>0</cdef_id>
				<vdef_id>0</vdef_id>
				<shift></shift>
				<value></value>
				<gprint_id>hash_060101e9c43831e54eca8069317a2ce8c6f751</gprint_id>
				<textalign></textalign>
				<text_format></text_format>
				<hard_return></hard_return>
				<line_width>1.00</line_width>
				<dashes></dashes>
				<dash_offset>0</dash_offset>
				<sequence>9</sequence>
			</hash_100101fd1f89bda6ca439507b8b10a6895ef83>
			<hash_100101204c34152b67dada375e7a147ebe7b3f>
				<graph_type_id>4</graph_type_id>
				<task_item_id>hash_0801010ee6bb54957f6795a5369a29f818d860</task_item_id>
				<color_id>E41B17</color_id>
				<alpha>FF</alpha>
				<consolidation_function_id>1</consolidation_function_id>
				<cdef_id>0</cdef_id>
				<vdef_id>0</vdef_id>
				<shift></shift>
				<value></value>
				<gprint_id>hash_060101e9c43831e54eca8069317a2ce8c6f751</gprint_id>
				<textalign></textalign>
				<text_format></text_format>
				<hard_return></hard_return>
				<line_width>1.00</line_width>
				<dashes></dashes>
				<dash_offset>0</dash_offset>
				<sequence>10</sequence>
			</hash_100101204c34152b67dada375e7a147ebe7b3f>
		</items>
		<inputs>
			<hash_09010186bd8819d830a81d64267761e1fd8ec4>
				<name>Total Disk Space Data Source</name>
				<description></description>
				<column_name>task_item_id</column_name>
				<items>hash_000101d80e4a4901ab86ee39c9cc613e13532f|hash_000101567c2214ee4753aa712c3d101ea49a5d|hash_000101ba0b6a9e316ef9be66abba68b80f7587|hash_0001014b8e4a6bf2757f04c3e3a088338a2f7a|hash_000101fd1f89bda6ca439507b8b10a6895ef83</items>
			</hash_09010186bd8819d830a81d64267761e1fd8ec4>
			<hash_0901016c8967850102202de166951e4411d426>
				<name>Used Disk Space Data Source</name>
				<description></description>
				<column_name>task_item_id</column_name>
				<items>hash_00010116d6a9a7f608762ad65b0841e5ef4e9c|hash_0001012c35b5cae64c5f146a55fcb416dd14b5|hash_00010136fa8063df3b07cece878d54443db727|hash_000101b7b381d47972f836785d338a3bef6661|hash_000101204c34152b67dada375e7a147ebe7b3f</items>
			</hash_0901016c8967850102202de166951e4411d426>
		</inputs>
	</hash_0001017489e44466abee8a7d8636cb2cb14a1a>
	<hash_010101d814fa3b79bd0f8933b6e0834d3f16d0>
		<name>Host MIB - Hard Drive Space</name>
		<ds>
			<t_name></t_name>
			<name>|host_description| - Hard Drive Space</name>
			<data_source_path></data_source_path>
			<data_input_id>hash_030101332111d8b54ac8ce939af87a7eac0c06</data_input_id>
			<t_data_source_profile_id></t_data_source_profile_id>
			<data_source_profile_id>hash_20010148f01ca42a88cfc169d019312cb6f70f</data_source_profile_id>
			<t_rrd_step></t_rrd_step>
			<rrd_step>60</rrd_step>
			<t_active></t_active>
			<active>on</active>
		</ds>
		<items>
			<hash_0801010ee6bb54957f6795a5369a29f818d860>
				<t_data_source_name></t_data_source_name>
				<data_source_name>hdd_used</data_source_name>
				<t_rrd_minimum></t_rrd_minimum>
				<rrd_minimum>0</rrd_minimum>
				<t_rrd_maximum></t_rrd_maximum>
				<rrd_maximum>0</rrd_maximum>
				<t_data_source_type_id></t_data_source_type_id>
				<data_source_type_id>1</data_source_type_id>
				<t_rrd_heartbeat></t_rrd_heartbeat>
				<rrd_heartbeat>120</rrd_heartbeat>
				<t_data_input_field_id></t_data_input_field_id>
				<data_input_field_id>0</data_input_field_id>
			</hash_0801010ee6bb54957f6795a5369a29f818d860>
			<hash_080101165a0da5f461561c85d092dfe96b9551>
				<t_data_source_name></t_data_source_name>
				<data_source_name>hdd_total</data_source_name>
				<t_rrd_minimum></t_rrd_minimum>
				<rrd_minimum>0</rrd_minimum>
				<t_rrd_maximum></t_rrd_maximum>
				<rrd_maximum>0</rrd_maximum>
				<t_data_source_type_id></t_data_source_type_id>
				<data_source_type_id>1</data_source_type_id>
				<t_rrd_heartbeat></t_rrd_heartbeat>
				<rrd_heartbeat>120</rrd_heartbeat>
				<t_data_input_field_id></t_data_input_field_id>
				<data_input_field_id>0</data_input_field_id>
			</hash_080101165a0da5f461561c85d092dfe96b9551>
		</items>
		<data>
			<item_000>
				<data_input_field_id>hash_07010192f5906c8dc0f964b41f4253df582c38</data_input_field_id>
				<t_value></t_value>
				<value></value>
			</item_000>
			<item_001>
				<data_input_field_id>hash_07010132285d5bf16e56c478f5e83f32cda9ef</data_input_field_id>
				<t_value></t_value>
				<value></value>
			</item_001>
			<item_002>
				<data_input_field_id>hash_070101172b4b0eacee4948c6479f587b62e512</data_input_field_id>
				<t_value>on</t_value>
				<value></value>
			</item_002>
			<item_003>
				<data_input_field_id>hash_07010130fb5d5bcf3d66bb5abe88596f357c26</data_input_field_id>
				<t_value>on</t_value>
				<value></value>
			</item_003>
			<item_004>
				<data_input_field_id>hash_07010131112c85ae4ff821d3b288336288818c</data_input_field_id>
				<t_value>on</t_value>
				<value></value>
			</item_004>
		</data>
	</hash_010101d814fa3b79bd0f8933b6e0834d3f16d0>
	<hash_030101332111d8b54ac8ce939af87a7eac0c06>
		<name>Get Script Server Data (Indexed)</name>
		<type_id>6</type_id>
		<input_string></input_string>
		<fields>
			<hash_070101172b4b0eacee4948c6479f587b62e512>
				<name>Index Type</name>
				<update_rra></update_rra>
				<regexp_match></regexp_match>
				<allow_nulls></allow_nulls>
				<type_code>index_type</type_code>
				<input_output>in</input_output>
				<data_name>index_type</data_name>
			</hash_070101172b4b0eacee4948c6479f587b62e512>
			<hash_07010130fb5d5bcf3d66bb5abe88596f357c26>
				<name>Index Value</name>
				<update_rra></update_rra>
				<regexp_match></regexp_match>
				<allow_nulls></allow_nulls>
				<type_code>index_value</type_code>
				<input_output>in</input_output>
				<data_name>index_value</data_name>
			</hash_07010130fb5d5bcf3d66bb5abe88596f357c26>
			<hash_07010131112c85ae4ff821d3b288336288818c>
				<name>Output Type ID</name>
				<update_rra></update_rra>
				<regexp_match></regexp_match>
				<allow_nulls></allow_nulls>
				<type_code>output_type</type_code>
				<input_output>in</input_output>
				<data_name>output_type</data_name>
			</hash_07010131112c85ae4ff821d3b288336288818c>
			<hash_0701015be8fa85472d89c621790b43510b5043>
				<name>Output Value</name>
				<update_rra>on</update_rra>
				<regexp_match></regexp_match>
				<allow_nulls></allow_nulls>
				<type_code></type_code>
				<input_output>out</input_output>
				<data_name>output</data_name>
			</hash_0701015be8fa85472d89c621790b43510b5043>
		</fields>
	</hash_030101332111d8b54ac8ce939af87a7eac0c06>
	<hash_20010148f01ca42a88cfc169d019312cb6f70f>
		<name>One-Minute Polling</name>
		<step>60</step>
		<heartbeat>120</heartbeat>
		<x_files_factor>0.5</x_files_factor>
		<default></default>
		<cf_items>1|2|3|4</cf_items>
		<items>
			<item_000>
				<name>Hourly @ 1 min</name>
				<steps>1</steps>
				<rows>10080</rows>
				<timespan>3600</timespan>
			</item_000>
			<item_001>
				<name>Daily @ 1 min</name>
				<steps>5</steps>
				<rows>8640</rows>
				<timespan>86400</timespan>
			</item_001>
			<item_002>
				<name>Weekly @ 1 min</name>
				<steps>30</steps>
				<rows>4320</rows>
				<timespan>604800</timespan>
			</item_002>
			<item_003>
				<name>Monthly @ 1 min</name>
				<steps>120</steps>
				<rows>2160</rows>
				<timespan>2618784</timespan>
			</item_003>
			<item_004>
				<name>Yearly @ 1 min</name>
				<steps>1440</steps>
				<rows>1461</rows>
				<timespan>31536000</timespan>
			</item_004>
		</items>
	</hash_20010148f01ca42a88cfc169d019312cb6f70f>
	<hash_060101e9c43831e54eca8069317a2ce8c6f751>
		<name>Normal</name>
		<gprint_text>%8.2lf %s</gprint_text>
	</hash_060101e9c43831e54eca8069317a2ce8c6f751>
</cacti>
